decision_tree_rap-0.1.1.dist-info/METADATA
decision_tree_rap-0.1.1.dist-info/WHEEL
decision_trees/__init__.py
decision_trees/classification.py
decision_tree_rap-0.1.1.dist-info/RECORD
